snetwork/__init__.py
snetwork/handler.py
snetwork/renderer.py
jupyter_snetwork-0.0.6.dist-info/METADATA
jupyter_snetwork-0.0.6.dist-info/WHEEL
jupyter_snetwork-0.0.6.dist-info/entry_points.txt
jupyter_snetwork-0.0.6.dist-info/licenses/LICENSE
jupyter_snetwork-0.0.6.dist-info/RECORD
