Metadata-Version: 2.4
Name: jupyter-snetwork
Version: 0.0.6
Summary: 
License-File: LICENSE
Author: Marcelo Hashimoto
Author-email: marcelo.hashimoto@gmail.com
Requires-Python: >=3.12,<4.0
Classifier: Programming Language :: Python :: 3
Classifier: Programming Language :: Python :: 3.12
Classifier: Programming Language :: Python :: 3.13
Classifier: Programming Language :: Python :: 3.14
Requires-Dist: jupyter-jchannel (>=0.3.9,<0.4.0)
Project-URL: Repository, https://github.com/hashiprobr/jupyter-snetwork
